{
  "accounts": [
    "created_at",
    "creator_id",
    "deleted_at",
    "email",
    "id",
    "is_verified",
    "password",
    "profile_name",
    "role",
    "updated_at",
    "userId"
  ],
  "accounts_backup_dev": [
    "created_at",
    "creator_id",
    "deleted_at",
    "email",
    "id",
    "is_verified",
    "password",
    "profile_name",
    "role",
    "updated_at",
    "userId"
  ],
  "api_logs": [
    "created_at",
    "duration_ms",
    "endpoint",
    "error_message",
    "id",
    "ip",
    "method",
    "status_code",
    "user_agent",
    "user_id"
  ],
  "auto_service_requests": [
    "assigned_at",
    "assigned_to",
    "created_at",
    "customer_email",
    "customer_location",
    "customer_name",
    "customer_phone",
    "description",
    "due_date",
    "external_id",
    "id",
    "internal_notes",
    "metadata",
    "priority",
    "property_tenant_id",
    "resolution_notes",
    "resolved_at",
    "source",
    "status",
    "tags",
    "title",
    "updated_at"
  ],
  "chat_logs": [
    "content",
    "created_at",
    "direction",
    "error_code",
    "error_reason",
    "id",
    "message_type",
    "metadata",
    "phone_number",
    "status",
    "user_id",
    "whatsapp_message_id"
  ],
  "chat_messages": [
    "content",
    "created_at",
    "deleted_at",
    "fileName",
    "fileUrl",
    "id",
    "isRead",
    "sender",
    "senderName",
    "service_request_id",
    "type",
    "updated_at"
  ],
  "invoice_line_items": [
    "amount",
    "created_at",
    "description",
    "id",
    "invoice_id"
  ],
  "invoice_payments": [
    "amount",
    "created_at",
    "id",
    "invoice_id",
    "payment_date",
    "payment_id",
    "payment_method",
    "reference"
  ],
  "invoices": [
    "amount_paid",
    "created_at",
    "credit_balance",
    "id",
    "invoice_date",
    "invoice_number",
    "kyc_application_id",
    "landlord_id",
    "notes",
    "offer_letter_id",
    "outstanding_balance",
    "property_id",
    "status",
    "tenant_id",
    "total_amount",
    "updated_at"
  ],
  "kyc": [
    "accept_terms_and_condition",
    "created_at",
    "deleted_at",
    "employers_address",
    "employers_name",
    "former_accomodation_type",
    "former_house_address",
    "guarantor",
    "guarantor_address",
    "guarantor_occupation",
    "guarantor_phone_number",
    "home_town",
    "id",
    "lga_of_origin",
    "marital_status",
    "monthly_income",
    "name_of_spouse",
    "nationality",
    "next_of_kin",
    "next_of_kin_address",
    "occupation",
    "reason_for_leaving",
    "religion",
    "state_of_origin",
    "updated_at",
    "user_id"
  ],
  "kyc_applications": [
    "additional_notes",
    "application_type",
    "available_property_ids",
    "business_address",
    "business_duration",
    "business_name",
    "business_proof_url",
    "contact_address",
    "created_at",
    "date_of_birth",
    "decision_made_at",
    "decision_made_ip",
    "deleted_at",
    "email",
    "employer_name",
    "employment_proof_url",
    "employment_status",
    "first_name",
    "form_opened_at",
    "form_opened_ip",
    "gender",
    "id",
    "id_document_url",
    "initial_property_id",
    "intended_use_of_property",
    "job_title",
    "kyc_link_id",
    "last_name",
    "length_of_employment",
    "marital_status",
    "monthly_net_income",
    "nationality",
    "nature_of_business",
    "next_of_kin_address",
    "next_of_kin_email",
    "next_of_kin_full_name",
    "next_of_kin_phone_number",
    "next_of_kin_relationship",
    "number_of_occupants",
    "occupation",
    "parking_needs",
    "passport_photo_url",
    "pending_kyc_id",
    "phone_number",
    "property_id",
    "proposed_rent_amount",
    "referral_agent_full_name",
    "referral_agent_phone_number",
    "religion",
    "rent_payment_frequency",
    "state_of_origin",
    "status",
    "tenant_id",
    "updated_at",
    "user_agent",
    "work_address",
    "work_phone_number"
  ],
  "kyc_feedback": [
    "comment",
    "created_at",
    "deleted_at",
    "id",
    "landlord_id",
    "property_name",
    "rating",
    "submitted_at",
    "tenant_email",
    "tenant_name",
    "updated_at"
  ],
  "kyc_links": [
    "created_at",
    "deleted_at",
    "expires_at",
    "id",
    "is_active",
    "landlord_id",
    "token",
    "updated_at"
  ],
  "kyc_otp": [
    "created_at",
    "expires_at",
    "id",
    "is_active",
    "is_verified",
    "kyc_token",
    "otp_code",
    "phone_number",
    "updated_at"
  ],
  "migrations": [
    "id",
    "name",
    "timestamp"
  ],
  "notice_agreement": [
    "additional_notes",
    "created_at",
    "deleted_at",
    "effective_date",
    "id",
    "notice_documents",
    "notice_id",
    "notice_image",
    "notice_type",
    "property_id",
    "property_name",
    "send_via",
    "status",
    "tenant_id",
    "tenant_name",
    "updated_at"
  ],
  "notification": [
    "created_at",
    "date",
    "deleted_at",
    "description",
    "id",
    "property_id",
    "service_request_id",
    "status",
    "type",
    "updated_at",
    "user_id"
  ],
  "offer_letters": [
    "acceptance_otp",
    "accepted_at",
    "accepted_by_phone",
    "agency_fee",
    "amount_paid",
    "branding",
    "caution_deposit",
    "content_snapshot",
    "created_at",
    "credit_balance",
    "decision_made_at",
    "decision_made_ip",
    "deleted_at",
    "form_opened_at",
    "form_opened_ip",
    "id",
    "kyc_application_id",
    "landlord_id",
    "legal_fee",
    "outstanding_balance",
    "payment_status",
    "pdf_generated_at",
    "pdf_url",
    "property_id",
    "rent_amount",
    "rent_frequency",
    "selected_at",
    "sent_at",
    "service_charge",
    "status",
    "tenancy_end_date",
    "tenancy_start_date",
    "terms_of_tenancy",
    "token",
    "total_amount",
    "updated_at"
  ],
  "password_reset_token": [
    "created_at",
    "expires_at",
    "id",
    "otp",
    "token",
    "user_id"
  ],
  "payment_logs": [
    "created_at",
    "event_data",
    "event_type",
    "id",
    "payment_id"
  ],
  "payments": [
    "amount",
    "created_at",
    "id",
    "metadata",
    "offer_letter_id",
    "paid_at",
    "payment_method",
    "payment_type",
    "paystack_access_code",
    "paystack_authorization_url",
    "paystack_reference",
    "renewal_invoice_id",
    "status",
    "updated_at"
  ],
  "properties": [
    "comment",
    "created_at",
    "deleted_at",
    "description",
    "id",
    "is_marketing_ready",
    "location",
    "name",
    "no_of_bathrooms",
    "no_of_bedrooms",
    "owner_id",
    "property_images",
    "property_status",
    "property_type",
    "rental_price",
    "security_deposit",
    "service_charge",
    "updated_at"
  ],
  "property_groups": [
    "created_at",
    "deleted_at",
    "id",
    "name",
    "owner_id",
    "property_ids",
    "updated_at"
  ],
  "property_histories": [
    "created_at",
    "deleted_at",
    "event_description",
    "event_type",
    "id",
    "monthly_rent",
    "move_in_date",
    "move_out_date",
    "move_out_reason",
    "owner_comment",
    "property_id",
    "related_entity_id",
    "related_entity_type",
    "tenant_comment",
    "tenant_id",
    "updated_at"
  ],
  "property_tenants": [
    "created_at",
    "deleted_at",
    "id",
    "property_id",
    "status",
    "tenant_id",
    "updated_at"
  ],
  "prospect_conversations": [
    "assigned_agent_id",
    "channel",
    "created_at",
    "deleted_at",
    "id",
    "intent",
    "interested_property_ids",
    "last_message_at",
    "phone_number",
    "preferences",
    "prospect_name",
    "schedule",
    "status",
    "summary",
    "updated_at",
    "web_session_id"
  ],
  "prospect_messages": [
    "content",
    "conversation_id",
    "created_at",
    "deleted_at",
    "direction",
    "id",
    "metadata",
    "sender_type",
    "updated_at"
  ],
  "push_subscriptions": [
    "auth",
    "created_at",
    "deleted_at",
    "endpoint",
    "id",
    "p256dh",
    "updated_at",
    "user_id"
  ],
  "query-result-cache": [
    "duration",
    "id",
    "identifier",
    "query",
    "result",
    "time"
  ],
  "query_logs": [
    "created_at",
    "duration_ms",
    "id",
    "is_slow",
    "parameters",
    "query",
    "query_type",
    "table_name"
  ],
  "receipts": [
    "amount_paid",
    "branding",
    "created_at",
    "deleted_at",
    "id",
    "invoice_number",
    "kyc_application_id",
    "notes",
    "offer_letter_id",
    "payment_id",
    "payment_method",
    "payment_reference",
    "pdf_url",
    "property_address",
    "property_id",
    "property_name",
    "receipt_date",
    "receipt_number",
    "tenant_email",
    "tenant_name",
    "tenant_phone",
    "token",
    "updated_at"
  ],
  "refresh_tokens": [
    "account_id",
    "created_at",
    "expires_at",
    "id",
    "ip_address",
    "is_revoked",
    "token",
    "user_agent"
  ],
  "renewal_invoices": [
    "amount_paid",
    "approval_status",
    "created_at",
    "deleted_at",
    "end_date",
    "expires_at",
    "id",
    "legal_fee",
    "other_charges",
    "otp_verified",
    "otp_verified_at",
    "outstanding_balance",
    "paid_at",
    "payment_frequency",
    "payment_method",
    "payment_option",
    "payment_reference",
    "payment_status",
    "property_id",
    "property_tenant_id",
    "receipt_number",
    "receipt_token",
    "rent_amount",
    "service_charge",
    "start_date",
    "tenant_id",
    "token",
    "token_type",
    "total_amount",
    "updated_at",
    "wallet_balance"
  ],
  "rent_increases": [
    "created_at",
    "current_rent",
    "deleted_at",
    "id",
    "initial_rent",
    "property_id",
    "reason",
    "rent_increase_date",
    "updated_at"
  ],
  "rents": [
    "amount_paid",
    "created_at",
    "deleted_at",
    "expiry_date",
    "id",
    "payment_frequency",
    "payment_status",
    "property_id",
    "rent_receipts",
    "rent_start_date",
    "rent_status",
    "rental_price",
    "security_deposit",
    "service_charge",
    "tenant_id",
    "updated_at"
  ],
  "scheduled_move_outs": [
    "created_at",
    "deleted_at",
    "effective_date",
    "id",
    "move_out_reason",
    "owner_comment",
    "processed",
    "processed_at",
    "property_id",
    "tenant_comment",
    "tenant_id",
    "updated_at"
  ],
  "service_request_status_history": [
    "change_reason",
    "changed_at",
    "changed_by_role",
    "changed_by_user_id",
    "created_at",
    "deleted_at",
    "id",
    "new_status",
    "notes",
    "previous_status",
    "service_request_id",
    "updated_at"
  ],
  "service_requests": [
    "assigned_to",
    "created_at",
    "date_reported",
    "deleted_at",
    "description",
    "id",
    "issue_category",
    "issue_images",
    "notes",
    "property_id",
    "property_name",
    "reopened_at",
    "request_id",
    "resolution_date",
    "resolvedAt",
    "status",
    "tenant_id",
    "tenant_name",
    "updated_at"
  ],
  "team": [
    "created_at",
    "creatorId",
    "deleted_at",
    "id",
    "name",
    "updated_at"
  ],
  "team_member": [
    "accountId",
    "created_at",
    "deleted_at",
    "email",
    "id",
    "permissions",
    "role",
    "teamId",
    "updated_at"
  ],
  "tenant_balance_ledger": [
    "balance_after",
    "balance_change",
    "created_at",
    "deleted_at",
    "description",
    "id",
    "landlord_id",
    "property_id",
    "related_entity_id",
    "related_entity_type",
    "tenant_id",
    "type",
    "updated_at"
  ],
  "tenant_balances": [
    "balance",
    "created_at",
    "deleted_at",
    "id",
    "landlord_id",
    "notes",
    "tenant_id",
    "updated_at"
  ],
  "tenant_kyc": [
    "admin_id",
    "business_address",
    "business_duration",
    "business_name",
    "contact_address",
    "created_at",
    "current_residence",
    "date_of_birth",
    "deleted_at",
    "email",
    "employer_name",
    "employment_status",
    "estimated_monthly_income",
    "first_name",
    "gender",
    "id",
    "job_title",
    "last_name",
    "length_of_employment",
    "marital_status",
    "monthly_net_income",
    "nationality",
    "nature_of_business",
    "next_of_kin_address",
    "next_of_kin_email",
    "next_of_kin_full_name",
    "next_of_kin_phone_number",
    "next_of_kin_relationship",
    "occupation",
    "phone_number",
    "referral_agent_full_name",
    "referral_agent_phone_number",
    "religion",
    "spouse_name_and_contact",
    "state_of_origin",
    "updated_at",
    "user_id",
    "work_address",
    "work_phone_number"
  ],
  "users": [
    "branding",
    "business_address",
    "business_duration",
    "business_monthly_income",
    "business_name",
    "business_website",
    "created_at",
    "creator_id",
    "date_of_birth",
    "deleted_at",
    "email",
    "employer_address",
    "employer_name",
    "employment_status",
    "first_name",
    "gender",
    "id",
    "is_verified",
    "job_title",
    "last_name",
    "lga",
    "logo_urls",
    "marital_status",
    "monthly_income",
    "monthly_income_estimate",
    "nationality",
    "nature_of_business",
    "offer_letter_template",
    "password",
    "phone_number",
    "preferences",
    "role",
    "source_of_funds",
    "spouse_employer",
    "spouse_full_name",
    "spouse_occupation",
    "spouse_phone_number",
    "state_of_origin",
    "updated_at",
    "work_email"
  ],
  "users_backup_dev": [
    "business_address",
    "business_monthly_income",
    "business_name",
    "business_website",
    "created_at",
    "creator_id",
    "date_of_birth",
    "deleted_at",
    "email",
    "employer_address",
    "employer_name",
    "employment_status",
    "first_name",
    "gender",
    "id",
    "is_verified",
    "job_title",
    "last_name",
    "lga",
    "logo_urls",
    "marital_status",
    "monthly_income",
    "monthly_income_estimate",
    "nationality",
    "nature_of_business",
    "password",
    "phone_number",
    "role",
    "source_of_funds",
    "spouse_employer",
    "spouse_full_name",
    "spouse_occupation",
    "spouse_phone_number",
    "state_of_origin",
    "updated_at",
    "work_email"
  ],
  "waitlist": [
    "created_at",
    "deleted_at",
    "full_name",
    "id",
    "option",
    "phone_number",
    "referral_name",
    "referral_phone_number",
    "updated_at"
  ],
  "whatsapp_notification_log": [
    "attempts",
    "created_at",
    "deleted_at",
    "id",
    "last_attempted_at",
    "last_error",
    "payload",
    "reference_id",
    "status",
    "type",
    "updated_at"
  ]
}